haystack_integrations/components/evaluators/py.typed
haystack_integrations/components/evaluators/ragas/__init__.py
haystack_integrations/components/evaluators/ragas/evaluator.py
ragas_haystack-3.0.0.dist-info/METADATA
ragas_haystack-3.0.0.dist-info/WHEEL
ragas_haystack-3.0.0.dist-info/licenses/LICENSE.txt
ragas_haystack-3.0.0.dist-info/RECORD
